toast-2.3.14.dist-info/RECORD
toast-2.3.14.dist-info/LICENSE
toast-2.3.14.dist-info/AUTHORS
toast-2.3.14.dist-info/WHEEL
toast-2.3.14.dist-info/top_level.txt
toast-2.3.14.dist-info/METADATA
toast/rng.py
toast/weather.py
toast/cache.py
toast/__init__.py
toast/vis.py
toast/op.py
toast/healpix.py
toast/timing.py
toast/mpi.py
toast/utils.py
toast/qarray.py
toast/schedule.py
toast/fft.py
toast/_libtoast.cpython-38-darwin.so
toast/dist.py
toast/todmap/pointing_math.py
toast/todmap/groundfilter.py
toast/todmap/sss.py
toast/todmap/mapmaker.py
toast/todmap/todmap_math.py
toast/todmap/conviqt.py
toast/todmap/__init__.py
toast/todmap/madam.py
toast/todmap/pointing.py
toast/todmap/mapsampler.py
toast/todmap/sim_det_dipole.py
toast/todmap/atm.py
toast/todmap/filterbin.py
toast/todmap/pysm.py
toast/todmap/sim_det_map.py
toast/todmap/sim_det_pysm.py
toast/todmap/sim_det_atm.py
toast/todmap/sim_tod.py
toast/tod/memorycounter.py
toast/tod/interval.py
toast/tod/spt3g.py
toast/tod/sim_interval.py
toast/tod/__init__.py
toast/tod/tod_math.py
toast/tod/crosstalk.py
toast/tod/spt3g_utils.py
toast/tod/noise.py
toast/tod/polyfilter.py
toast/tod/applygain.py
toast/tod/gainscrambler.py
toast/tod/sim_det_noise.py
toast/tod/sim_noise.py
toast/tod/tidas_utils.py
toast/tod/tidas.py
toast/tod/sim_focalplane.py
toast/tod/tod.py
toast/fod/noise_estimation.py
toast/fod/__init__.py
toast/fod/psd_math.py
toast/tests/map_satellite.py
toast/tests/ops_sim_sss.py
toast/tests/ops_madam.py
toast/tests/ops_polyfilter.py
toast/tests/runner.py
toast/tests/env.py
toast/tests/ops_dipole.py
toast/tests/ops_sim_pysm.py
toast/tests/spt3g.py
toast/tests/ops_groundfilter.py
toast/tests/ops_pmat.py
toast/tests/rng.py
toast/tests/ops_gainscrambler.py
toast/tests/ops_filterbin.py
toast/tests/ops_applygain.py
toast/tests/cache.py
toast/tests/__init__.py
toast/tests/intervals.py
toast/tests/cov.py
toast/tests/ops_crosstalk.py
toast/tests/map_ground.py
toast/tests/healpix.py
toast/tests/ops_sim_atm.py
toast/tests/timing.py
toast/tests/mpi.py
toast/tests/psd_math.py
toast/tests/tod_satellite.py
toast/tests/ops_simnoise.py
